nut2/__init__.py
nut2_notl-2.1.3.dist-info/licenses/LICENSE
nut2_notl-2.1.3.dist-info/METADATA
nut2_notl-2.1.3.dist-info/WHEEL
nut2_notl-2.1.3.dist-info/top_level.txt
nut2_notl-2.1.3.dist-info/RECORD
