Metadata-Version: 2.4
Name: nut2-notl
Version: 2.1.3
Summary: A Python abstraction class to access NUT servers.
Author-email: Ryan Shipp <python@rshipp.com>
License-Expression: GPL-3.0-or-later
Keywords: nut,ups
Classifier: Intended Audience :: Developers
Classifier: Intended Audience :: Information Technology
Classifier: Intended Audience :: System Administrators
Classifier: Operating System :: OS Independent
Classifier: Programming Language :: Python
Classifier: Programming Language :: Python :: 3
Classifier: Topic :: Software Development :: Libraries
Classifier: Topic :: System :: Power (UPS)
Classifier: Topic :: System :: Systems Administration
Requires-Python: >=3
License-File: LICENSE
Dynamic: license-file
